dirlay/__init__.py
dirlay/__init__.pyi
dirlay/__version__.py
dirlay/format_rich.py
dirlay/format_rich.pyi
dirlay/nested_dict.py
dirlay/nested_dict.pyi
dirlay/optional.py
dirlay/py.typed
dirlay/types.py
dirlay-0.4.0.dist-info/METADATA
dirlay-0.4.0.dist-info/WHEEL
dirlay-0.4.0.dist-info/licenses/LICENSE
dirlay-0.4.0.dist-info/RECORD
