Metadata-Version: 2.4
Name: dirlay
Version: 0.4.0
Summary: Directory layout object for testing and documentation
Project-URL: Documentation, https://dirlay.readthedocs.io
Project-URL: Homepage, https://github.com/makukha/dirlay
Project-URL: Repository, https://github.com/makukha/dirlay
Project-URL: Issues, https://github.com/makukha/dirlay/issues
Project-URL: Changelog, https://github.com/makukha/dirlay/blob/main/CHANGELOG.md
Author-email: Michael Makukha <m.makukha@gmail.com>
License: MIT
License-File: LICENSE
Keywords: directory,layout,structure,tree
Classifier: Development Status :: 4 - Beta
Classifier: Environment :: Console
Classifier: Intended Audience :: Developers
Classifier: License :: OSI Approved :: MIT License
Classifier: Operating System :: OS Independent
Classifier: Programming Language :: Python
Classifier: Programming Language :: Python :: 2
Classifier: Programming Language :: Python :: 2.7
Classifier: Programming Language :: Python :: 3
Classifier: Programming Language :: Python :: 3.5
Classifier: Programming Language :: Python :: 3.6
Classifier: Programming Language :: Python :: 3.7
Classifier: Programming Language :: Python :: 3.8
Classifier: Programming Language :: Python :: 3.9
Classifier: Programming Language :: Python :: 3.10
Classifier: Programming Language :: Python :: 3.11
Classifier: Programming Language :: Python :: 3.12
Classifier: Programming Language :: Python :: 3.13
Classifier: Programming Language :: Python :: 3.14
Classifier: Programming Language :: Python :: Implementation :: CPython
Classifier: Topic :: Documentation
Classifier: Topic :: Software Development
Classifier: Topic :: Software Development :: Libraries
Classifier: Typing :: Typed
Requires-Python: !=3.0,!=3.1,!=3.2,!=3.3,!=3.4,>=2.7
Requires-Dist: pathlib2>=2.3.7.post1; python_version < '3'
Provides-Extra: rich
Requires-Dist: rich>=9.7; (python_version >= '3.6') and extra == 'rich'
